browser_use_akimoto/README.md
browser_use_akimoto/__init__.py
browser_use_akimoto/logging_config.py
browser_use_akimoto/utils.py
browser_use_akimoto/agent/prompts.py
browser_use_akimoto/agent/service.py
browser_use_akimoto/agent/tests.py
browser_use_akimoto/agent/views.py
browser_use_akimoto/agent/message_manager/service.py
browser_use_akimoto/agent/message_manager/tests.py
browser_use_akimoto/agent/message_manager/views.py
browser_use_akimoto/browser/browser.py
browser_use_akimoto/browser/context.py
browser_use_akimoto/browser/views.py
browser_use_akimoto/browser/tests/screenshot_test.py
browser_use_akimoto/browser/tests/test_clicks.py
browser_use_akimoto/controller/service.py
browser_use_akimoto/controller/views.py
browser_use_akimoto/controller/registry/service.py
browser_use_akimoto/controller/registry/views.py
browser_use_akimoto/dom/__init__.py
browser_use_akimoto/dom/buildDomTree.js
browser_use_akimoto/dom/service.py
browser_use_akimoto/dom/views.py
browser_use_akimoto/dom/history_tree_processor/service.py
browser_use_akimoto/dom/history_tree_processor/view.py
browser_use_akimoto/dom/tests/extraction_test.py
browser_use_akimoto/dom/tests/process_dom_test.py
browser_use_akimoto/telemetry/service.py
browser_use_akimoto/telemetry/views.py
browser_use_akimoto-1.0.1.dist-info/METADATA
browser_use_akimoto-1.0.1.dist-info/WHEEL
browser_use_akimoto-1.0.1.dist-info/licenses/LICENSE
browser_use_akimoto-1.0.1.dist-info/RECORD
